{"stats":{"minecraft:mined":{"minecraft:seagrass":2,"iguanatweaksexpanded:charcoal_layer":2,"minecraft:tall_seagrass":1,"iguanatweaksexpanded:flint_rock":26,"minecraft:dandelion":1,"treechop:chopped_log":4,"minecraft:clay":6,"minecraft:grass":278,"projectvibrantjourneys:twigs":16,"lititup:switchgrass":10,"projectvibrantjourneys:short_grass":36,"ytech:thatch":1,"projectvibrantjourneys:mossy_rocks":1,"minecraft:stripped_oak_log":2,"ytech:grass_bed":1,"minecraft:fern":5},"minecraft:used":{"minecraft:oak_log":6,"minecraft:apple":3,"dens_addition:flint_axe":26,"dens_addition:flint_shovel":10,"primalstorage:oak_shelves":1,"ytech:grass_bed":2,"farmersdelight:flint_knife":283,"ytech:thatch":1,"minecraft:dandelion":1},"minecraft:picked_up":{"minecraft:stripped_oak_log":2,"projectvibrantjourneys:light_brown_bark_mushroom":3,"minecraft:charcoal":2,"minecraft:stick":22,"minecraft:clay_ball":24,"minecraft:dandelion":1,"lititup:switchgrass_fiber":8,"ytech:grass_bed":2,"minecraft:porkchop":1,"minecraft:flint":26,"ytech:brick_mold":3,"minecraft:oak_log":22,"ytech:unfired_brick":12,"dens_addition:flint_axe":1,"minecraft:apple":3,"minecraft:wheat_seeds":2,"farmersdelight:straw":42,"minecraft:oak_sapling":9,"minecraft:white_wool":1,"primalstorage:oak_shelves":1,"ytech:thatch":1},"minecraft:killed":{"naturalist:boar":1,"minecraft:sheep":2},"minecraft:dropped":{"dens_addition:flint_axe":1},"minecraft:broken":{"dens_addition:flint_axe":1},"minecraft:crafted":{"dens_addition:fire_wood":12,"ytech:thatch":4,"farmersdelight:flint_knife":1,"minecraft:brown_dye":3,"ytech:wooden_plate":5,"ytech:grass_twine":5,"ytech:wooden_bolt":6,"lititup:sparkling_flint":1,"dens_addition:flint_axe":2,"dens_addition:flint_shovel":1},"minecraft:custom":{"minecraft:time_since_rest":30786,"minecraft:sprint_one_cm":35692,"minecraft:damage_taken":110,"minecraft:walk_one_cm":106690,"minecraft:mob_kills":3,"minecraft:drop":1,"minecraft:damage_dealt":461,"minecraft:swim_one_cm":2594,"minecraft:fly_one_cm":28553,"minecraft:interact_with_campfire":4,"minecraft:crouch_one_cm":630,"minecraft:play_time":30786,"minecraft:sneak_time":823,"minecraft:walk_under_water_one_cm":1151,"minecraft:jump":339,"minecraft:leave_game":8,"minecraft:time_since_death":30786,"minecraft:walk_on_water_one_cm":719,"minecraft:total_world_time":35094,"minecraft:fall_one_cm":2417}},"DataVersion":3465}